LICENSE
MANIFEST.in
README.md
requirements.txt
setup.py
pyg_extension/__init__.py
pyg_extension.egg-info/PKG-INFO
pyg_extension.egg-info/SOURCES.txt
pyg_extension.egg-info/dependency_links.txt
pyg_extension.egg-info/requires.txt
pyg_extension.egg-info/top_level.txt
pyg_extension/data/__init__.py
pyg_extension/data/dataset.py
pyg_extension/data/morse.py
pyg_extension/data/structuretodata.py
pyg_extension/nn/__init__.py
pyg_extension/nn/basemodel.py
pyg_extension/nn/flow_geo.py
pyg_extension/nn/general.py
pyg_extension/nn/resnet.py
pyg_extension/transforms/__init__.py
pyg_extension/transforms/distribureedgeattr.py
pyg_extension/transforms/gaussiansmearing.py
pyg_extension/transforms/state.py
pyg_extension/utils/__init__.py
pyg_extension/utils/log_model.py
pyg_extension/utils/separate.py
test/test_cgcnn.py
test/test_resnet.py
test/test_schnet.py
test/test_structuretodata.py