Metadata-Version: 2.1
Name: pyg-extension
Version: 0.0.4
Summary: Crystal extension for pytorch_geometric
Author: wangchangxin
Author-email: 986798607@qq.com
Maintainer: wangchangxin
License: UNKNOWN
Platform: Windows
Platform: Unix
Classifier: Development Status :: 4 - Beta
Classifier: Intended Audience :: Science/Research
Classifier: Natural Language :: English
Classifier: Operating System :: Microsoft :: Windows
Classifier: Operating System :: Unix
Classifier: Programming Language :: Python :: 3.6
Classifier: Programming Language :: Python :: 3.7
Classifier: Programming Language :: Python :: 3.8
Classifier: Programming Language :: Python :: 3.9
Classifier: Programming Language :: Python :: 3.10
Requires-Python: >=3.6
License-File: LICENSE
